jupyter_ydoc/__init__.py
jupyter_ydoc/_version.py
jupyter_ydoc/py.typed
jupyter_ydoc/utils.py
jupyter_ydoc/ybasedoc.py
jupyter_ydoc/yblob.py
jupyter_ydoc/yfile.py
jupyter_ydoc/ynotebook.py
jupyter_ydoc/yunicode.py
jupyter_ydoc-3.1.0.dist-info/METADATA
jupyter_ydoc-3.1.0.dist-info/WHEEL
jupyter_ydoc-3.1.0.dist-info/entry_points.txt
jupyter_ydoc-3.1.0.dist-info/licenses/LICENSE
jupyter_ydoc-3.1.0.dist-info/RECORD
