Metadata-Version: 2.4
Name: jupyter-ydoc
Version: 3.1.0
Summary: Document structures for collaborative editing using Ypy
Project-URL: Homepage, https://jupyter.org
Project-URL: Source, https://github.com/jupyter-server/jupyter_ydoc
Author-email: Jupyter Development Team <jupyter@googlegroups.com>
License: BSD 3-Clause License
License-File: LICENSE
Keywords: jupyter,pycrdt,yjs
Requires-Python: >=3.8
Requires-Dist: importlib-metadata>=3.6; python_version < '3.10'
Requires-Dist: pycrdt<0.13.0,>=0.10.1
Provides-Extra: dev
Requires-Dist: click; extra == 'dev'
Requires-Dist: jupyter-releaser; extra == 'dev'
Requires-Dist: pre-commit; extra == 'dev'
Provides-Extra: docs
Requires-Dist: myst-parser; extra == 'docs'
Requires-Dist: pydata-sphinx-theme; extra == 'docs'
Requires-Dist: sphinx; extra == 'docs'
Provides-Extra: test
Requires-Dist: httpx-ws>=0.5.2; extra == 'test'
Requires-Dist: hypercorn>=0.16.0; extra == 'test'
Requires-Dist: pre-commit; extra == 'test'
Requires-Dist: pycrdt-websocket<0.16.0,>=0.15.0; extra == 'test'
Requires-Dist: pytest; extra == 'test'
Requires-Dist: pytest-asyncio; extra == 'test'
